flatpaksync/__init__.py
flatpaksync/compareapp.py
flatpaksync/comparepermission.py
flatpaksync/comparerepo.py
flatpaksync/flatpakcmd.py
flatpaksync/main.py
flatpaksync/actions/__init__.py
flatpaksync/actions/app.py
flatpaksync/actions/mask.py
flatpaksync/actions/permission.py
flatpaksync/actions/repo.py
flatpaksync/commands/__init__.py
flatpaksync/commands/add.py
flatpaksync/commands/command.py
flatpaksync/commands/generate.py
flatpaksync/commands/remove.py
flatpaksync/commands/run.py
flatpaksync/configs/__init__.py
flatpaksync/configs/read.py
flatpaksync/configs/write.py
flatpaksync/parsers/__init__.py
flatpaksync/parsers/app.py
flatpaksync/parsers/mask.py
flatpaksync/parsers/permission.py
flatpaksync/parsers/repo.py
flatpaksync/structs/__init__.py
flatpaksync/structs/app.py
flatpaksync/structs/applist.py
flatpaksync/structs/permission.py
flatpaksync/structs/permissionlist.py
flatpaksync/structs/repo.py
flatpaksync/structs/repolist.py
flatpaksync/structs/settings.py
flatpak_sync-1.0.3.dist-info/LICENSE
flatpak_sync-1.0.3.dist-info/METADATA
flatpak_sync-1.0.3.dist-info/WHEEL
flatpak_sync-1.0.3.dist-info/entry_points.txt
flatpak_sync-1.0.3.dist-info/top_level.txt
flatpak_sync-1.0.3.dist-info/RECORD
