Metadata-Version: 2.1
Name: flatpak-sync
Version: 1.0.3
Summary: Automate installation of Flatpak Applications, Permissions and Repositories
Home-page: https://github.com/jeteokeeffe/flatpak-sync
Author: JJO
Author-email: jeteokeeffe@yahoo.com
License: UNKNOWN
Platform: UNKNOWN
Classifier: Programming Language :: Python :: 3
Classifier: License :: OSI Approved :: MIT License
Classifier: Operating System :: POSIX :: Linux
Requires-Python: >=3.6
Requires-Dist: Click
